README.md
setup.py
pytorch_rl.egg-info/PKG-INFO
pytorch_rl.egg-info/SOURCES.txt
pytorch_rl.egg-info/dependency_links.txt
pytorch_rl.egg-info/requires.txt
pytorch_rl.egg-info/top_level.txt
rl/__init__.py
rl/agents/__init__.py
rl/agents/ddpg.py
rl/agents/ddqn.py
rl/common/__init__.py
rl/common/ounoise.py
rl/common/replaybuffer.py
rl/models/__init__.py
rl/models/ddpg/__init__.py
rl/models/ddpg/actor.py
rl/models/ddpg/critic.py
rl/models/ddqn/__init__.py
rl/models/ddqn/critic_cartpole.py