Metadata-Version: 1.0
Name: pytorch-rl
Version: 0.0.1
Summary: Reinforcement Learning using PyTorch
Home-page: https://github.com/khushhallchandra/pytorch-rl
Author: Khushhall Chandra Mahajan, Pulkit Katdare 
Author-email: kcm00000@gmail.com, radiantpulkit@gmail.com
License: MIT
Platform: UNKNOWN
